zoho_api_client-0.1.0.dist-info/licenses/LICENCE.md
zoho_client/__init__.py
zoho_client/auth.py
zoho_client/client.py
zoho_client/exceptions.py
zoho_client/utils.py
zoho_client/modules/__init__.py
zoho_client/modules/base.py
zoho_client/modules/books.py
zoho_client/modules/crm.py
zoho_client/modules/inventory.py
zoho_api_client-0.1.0.dist-info/METADATA
zoho_api_client-0.1.0.dist-info/WHEEL
zoho_api_client-0.1.0.dist-info/top_level.txt
zoho_api_client-0.1.0.dist-info/RECORD
