Metadata-Version: 2.4
Name: zoho-api-client
Version: 0.1.0
Summary: Cliente Python para las APIs de Zoho
Home-page: https://github.com/CodeDeveloperV/zoho-api-client
Author: Victor
Author-email: Victor <tu@email.com>
License: MIT
Project-URL: Homepage, https://github.com/CodeDeveloperV/zoho-api-client
Project-URL: Documentation, https://github.com/CodeDeveloperV/zoho-api-client#readme
Project-URL: Repository, https://github.com/CodeDeveloperV/zoho-api-client
Project-URL: Issues, https://github.com/CodeDeveloperV/zoho-api-client/issues
Keywords: zoho,api,crm,books,inventory
Classifier: Development Status :: 3 - Alpha
Classifier: Intended Audience :: Developers
Classifier: License :: OSI Approved :: MIT License
Classifier: Programming Language :: Python :: 3
Classifier: Programming Language :: Python :: 3.9
Classifier: Programming Language :: Python :: 3.10
Classifier: Programming Language :: Python :: 3.11
Classifier: Programming Language :: Python :: 3.12
Classifier: Programming Language :: Python :: 3.13
Requires-Python: >=3.9
License-File: LICENCE.md
Requires-Dist: requests>=2.31.0
Provides-Extra: dev
Requires-Dist: pytest>=7.4.0; extra == "dev"
Requires-Dist: pytest-cov>=4.1.0; extra == "dev"
Requires-Dist: pytest-mock>=3.12.0; extra == "dev"
Requires-Dist: black>=24.0.0; extra == "dev"
Requires-Dist: ruff>=0.1.0; extra == "dev"
Requires-Dist: mypy>=1.8.0; extra == "dev"
Requires-Dist: types-requests>=2.31.0; extra == "dev"
Dynamic: author
Dynamic: home-page
Dynamic: license-file
Dynamic: requires-python
